README.txt
setup.py
rightarrow/__init__.py
rightarrow/annotations.py
rightarrow/constraintgen.py
rightarrow/constraintsolve.py
rightarrow/enforce.py
rightarrow/lexer.py
rightarrow/parser.py
rightarrow.egg-info/PKG-INFO
rightarrow.egg-info/SOURCES.txt
rightarrow.egg-info/dependency_links.txt
rightarrow.egg-info/requires.txt
rightarrow.egg-info/top_level.txt