Metadata-Version: 1.0
Name: rightarrow
Version: 0.4
Summary: A language for describing Python programs with concise higher-order annotations like "(a -> a) -> [a] -> [a]" but don't you dare call them "types"
Home-page: https://github.com/kennknowles/python-rightarrow
Author: Kenneth Knowles
Author-email: kenn.knowles@gmail.com
License: Apache 2.0
Platform: UNKNOWN
